bencodingpy/__init__.py
bencodingpy/decoding.py
bencodingpy/encoding.py
bencodingpy/exceptions.py
bencodingpy-1.0.2.dist-info/METADATA
bencodingpy-1.0.2.dist-info/WHEEL
bencodingpy-1.0.2.dist-info/licenses/COPYING
bencodingpy-1.0.2.dist-info/RECORD
