Metadata-Version: 2.3
Name: bencodingpy
Version: 1.0.2
Summary: Simple bencoding decode/encode library
Project-URL: Documentation, https://github.com/abelgarcia2/bencodingpy/readme
Project-URL: Issues, https://github.com/abelgarcia2/bencodingpy/issues
Project-URL: Source, https://github.com/abelgarcia2/bencodingpy
Author: Abel García
License-Expression: MIT
License-File: COPYING
Keywords: BEP 003,BEP 3,bdecode,bdecoding,bencode,bencoding,bep_003,bittorrent,p2p
Classifier: Development Status :: 5 - Production/Stable
Classifier: Intended Audience :: Developers
Classifier: License :: OSI Approved :: GNU General Public License v3 (GPLv3)
Classifier: Programming Language :: Python
Classifier: Programming Language :: Python :: 3.8
Classifier: Programming Language :: Python :: 3.9
Classifier: Programming Language :: Python :: 3.10
Classifier: Programming Language :: Python :: 3.11
Classifier: Programming Language :: Python :: 3.12
Classifier: Programming Language :: Python :: Implementation :: CPython
Classifier: Programming Language :: Python :: Implementation :: PyPy
Classifier: Topic :: Communications :: File Sharing
Classifier: Topic :: Software Development :: Libraries
Requires-Python: >=3.8
